{"key":"content:en:pricing:index.md","generatedAt":"2022-06-02T03:42:59.504Z","mtime":"2022-06-02T03:42:59.502Z","slug":"","title":"Pricing","position":"999999990000","to":"/pricing","draft":false,"page":true,"language":"en","template":"blank","description":"Nuxt is an MIT licensed open source project and free to use. However, the maintenance effort is not sustainable without proper financial backing.","empty":false,"body":{"raw":"---\ntemplate: blank\ntitle: Pricing\ndescription: \"Nuxt is an MIT licensed open source project and free to use. However, the maintenance effort is not sustainable without proper financial backing.\"\n---\n\n\n\n\n::suger-home-pricing\n#title\nSimple plans to grow your business\n#pricing-card\n::suger-home-text-list\n---\ntextList: ['Features included','Multi Cloud marketplace integrations\n','Users - Unlimited','New Product listing - Unlimited','New private offer - Unlimited\n','Easy metering & billing - Unlimited','Contract upsell, renew & conversion - Unlimited','Access to Suger API s']\nbkColor: bg-white\ntextColor: '#2a1b49'\ntitleColor: '#000'\nsubtitleColor: '#000'\n---\n#title\nSmall & Medium Business\n#subtitle\nAlways Free\n::\n\n::suger-home-text-list\n---\ntextList: ['Features included','All features in SMB plan','Premium support and services / SLAs','Dedicated account manager','Dedicated onboarding','Sell with Resellers & Partners','Customize based your request']\nbkColor: bg-purple-900\ntextColor: '#ffffff'\ntitleColor: '#ffffff'\nsubtitleColor: '#ffffff'\n---\n#title\nEnterprise\n#subtitle\nContact Sales\n::\n\n::","ast":{"type":"root","children":[{"type":"element","tag":"suger-home-pricing","props":{},"children":[{"type":"element","tag":"template","props":{"v-slot:title":""},"children":[{"type":"element","tag":"prose-paragraph","props":{},"children":[{"type":"text","value":"Simple plans to grow your business"}]}],"content":[{"type":"element","tag":"prose-paragraph","props":{},"children":[{"type":"text","value":"Simple plans to grow your business"}]}]},{"type":"element","tag":"template","props":{"v-slot:pricing-card":""},"children":[{"type":"element","tag":"suger-home-text-list","props":{":textList":"[\"Features included\",\"Multi Cloud marketplace integrations \",\"Users - Unlimited\",\"New Product listing - Unlimited\",\"New private offer - Unlimited \",\"Easy metering & billing - Unlimited\",\"Contract upsell, renew & conversion - Unlimited\",\"Access to Suger API s\"]","bkColor":"bg-white","subtitleColor":"#000","textColor":"#2a1b49","titleColor":"#000"},"children":[{"type":"element","tag":"template","props":{"v-slot:title":""},"children":[{"type":"element","tag":"prose-paragraph","props":{},"children":[{"type":"text","value":"Small & Medium Business"}]}],"content":[{"type":"element","tag":"prose-paragraph","props":{},"children":[{"type":"text","value":"Small & Medium Business"}]}]},{"type":"element","tag":"template","props":{"v-slot:subtitle":""},"children":[{"type":"element","tag":"prose-paragraph","props":{},"children":[{"type":"text","value":"Always Free"}]}],"content":[{"type":"element","tag":"prose-paragraph","props":{},"children":[{"type":"text","value":"Always Free"}]}]}]},{"type":"element","tag":"suger-home-text-list","props":{":textList":"[\"Features included\",\"All features in SMB plan\",\"Premium support and services / SLAs\",\"Dedicated account manager\",\"Dedicated onboarding\",\"Sell with Resellers & Partners\",\"Customize based your request\"]","bkColor":"bg-purple-900","subtitleColor":"#ffffff","textColor":"#ffffff","titleColor":"#ffffff"},"children":[{"type":"element","tag":"template","props":{"v-slot:title":""},"children":[{"type":"element","tag":"prose-paragraph","props":{},"children":[{"type":"text","value":"Enterprise"}]}],"content":[{"type":"element","tag":"prose-paragraph","props":{},"children":[{"type":"text","value":"Enterprise"}]}]},{"type":"element","tag":"template","props":{"v-slot:subtitle":""},"children":[{"type":"element","tag":"prose-paragraph","props":{},"children":[{"type":"text","value":"Contact Sales"}]}],"content":[{"type":"element","tag":"prose-paragraph","props":{},"children":[{"type":"text","value":"Contact Sales"}]}]}]}],"content":[{"type":"element","tag":"suger-home-text-list","props":{":textList":"[\"Features included\",\"Multi Cloud marketplace integrations \",\"Users - Unlimited\",\"New Product listing - Unlimited\",\"New private offer - Unlimited \",\"Easy metering & billing - Unlimited\",\"Contract upsell, renew & conversion - Unlimited\",\"Access to Suger API s\"]","bkColor":"bg-white","subtitleColor":"#000","textColor":"#2a1b49","titleColor":"#000"},"children":[{"type":"element","tag":"template","props":{"v-slot:title":""},"children":[{"type":"element","tag":"prose-paragraph","props":{},"children":[{"type":"text","value":"Small & Medium Business"}]}],"content":[{"type":"element","tag":"prose-paragraph","props":{},"children":[{"type":"text","value":"Small & Medium Business"}]}]},{"type":"element","tag":"template","props":{"v-slot:subtitle":""},"children":[{"type":"element","tag":"prose-paragraph","props":{},"children":[{"type":"text","value":"Always Free"}]}],"content":[{"type":"element","tag":"prose-paragraph","props":{},"children":[{"type":"text","value":"Always Free"}]}]}]},{"type":"element","tag":"suger-home-text-list","props":{":textList":"[\"Features included\",\"All features in SMB plan\",\"Premium support and services / SLAs\",\"Dedicated account manager\",\"Dedicated onboarding\",\"Sell with Resellers & Partners\",\"Customize based your request\"]","bkColor":"bg-purple-900","subtitleColor":"#ffffff","textColor":"#ffffff","titleColor":"#ffffff"},"children":[{"type":"element","tag":"template","props":{"v-slot:title":""},"children":[{"type":"element","tag":"prose-paragraph","props":{},"children":[{"type":"text","value":"Enterprise"}]}],"content":[{"type":"element","tag":"prose-paragraph","props":{},"children":[{"type":"text","value":"Enterprise"}]}]},{"type":"element","tag":"template","props":{"v-slot:subtitle":""},"children":[{"type":"element","tag":"prose-paragraph","props":{},"children":[{"type":"text","value":"Contact Sales"}]}],"content":[{"type":"element","tag":"prose-paragraph","props":{},"children":[{"type":"text","value":"Contact Sales"}]}]}]}]}]}]},"toc":{"title":"","searchDepth":2,"depth":2,"links":[]}}}