{"key":"content:en:index.md","generatedAt":"2022-06-02T03:42:59.279Z","mtime":"2022-06-02T03:42:59.274Z","slug":"","title":"The Intuitive Vue Framework","position":"999900000000","to":"/","draft":false,"page":true,"language":"en","template":"blank","description":"Build your next Vue.js application with confidence using Nuxt. An open source framework making web development simple and powerful.","bgClass":"bg-white","empty":false,"body":{"raw":"---\ntemplate: blank\ntitle: 'The Intuitive Vue Framework'\ndescription: 'Build your next Vue.js application with confidence using Nuxt. An open source framework making web development simple and powerful.'\nbgClass: 'bg-white'\n---\n<!-- 两个::表示引用组件 -->\n::home-hero\n#title\nAccelerate your SaaS Monetization<br>on Multi Cloud Marketplaces\n\n::\n\n<!-- suger home main img -->\n::suger-main-img\n::\n\n::suger-home-features\n\n::section-content-item\n---\ntitle: Easy metering\ndescription: You can use our console to report usage of your all your entitlements. We will make sure upload these reports for you to the cloud marketplace.\nimage: https://uploads-ssl.webflow.com/6280284db2137d2c42b7c4b1/6280284db2137d52aab7c4ed_icons8-check-dollar-96%201.png\n---\n::\n\n::section-content-item\n---\ntitle: No Code onboarding\ndescription: You don't need an engineer team to help you build payment to start  monetization. Just grant us access to your cloud and we will do all the onboarding for you.\nimage: https://uploads-ssl.webflow.com/6280284db2137d2c42b7c4b1/6280284db2137db099b7c4f0_icons8-secure-96%201.png\n---\n::\n\n::section-content-item\n---\ntitle: Increase your sales\ndescription: Many business shift their SaaS purchase from local to cloud for easy management. By listing your product on cloud marketplace, you have access to a major audience.\nimage: https://uploads-ssl.webflow.com/6280284db2137d2c42b7c4b1/6280284db2137d52aab7c4ed_icons8-check-dollar-96%201.png\n---\n::\n\n\n::section-content-item\n---\ntitle: Manage your contracts\ndescription: On our console, you can easily identify the potential audience for conversion, renewal and upsell opportunity.\nimage: https://uploads-ssl.webflow.com/6280284db2137d2c42b7c4b1/6280284db2137d52aab7c4ed_icons8-check-dollar-96%201.png\n---\n::\n\n\n\n#title\nCheck our main features\n\n#description\nSuger is the solution to help cloud marketplace SaaS seller integrate with cloud marketplace much faster & easier. We enable SaaS companies of all sizes to boost their SaaS monetization via the cloud marketplace.\n::\n\n::suger-home-product\n---\ncategory: Partners\n---\n\n<!-- #title\nSustainable [_Development_]{.text-primary} -->\n\n<!-- #description -->\n<!-- Nuxt development is carried out by passionate developers, but the amount of effort needed to maintain and develop new features is not sustainable without proper financial backing. We are thankful for our sponsors and partners, who help make Nuxt possible.<br> -->\n\n#partners-card\n\n::suger-home-img\n---\nicon: 'https://uploads-ssl.webflow.com/6280284db2137d2c42b7c4b1/62803e0239e6f50160d2e67d_Screen%20Shot%202022-05-14%20at%204.40.38%20PM.png'\ncategory: img\nsrcset: https://uploads-ssl.webflow.com/6280284db2137d2c42b7c4b1/62803e0239e6f50160d2e67d_Screen%20Shot%202022-05-14%20at%204.40.38%20PM-p-500.png 500w, https://uploads-ssl.webflow.com/6280284db2137d2c42b7c4b1/62803e0239e6f50160d2e67d_Screen%20Shot%202022-05-14%20at%204.40.38%20PM-p-800.png 800w, https://uploads-ssl.webflow.com/6280284db2137d2c42b7c4b1/62803e0239e6f50160d2e67d_Screen%20Shot%202022-05-14%20at%204.40.38%20PM.png 998w\n---\n::\n\n::suger-home-text\n#title\nTechnology partners\n\n#description\nTechnology partners offer services that empower Nuxt developers, such as CMS, Hosting, Database, and more.\n::\n\n::suger-home-text\n#title\nEasy metering\n\n#description\nYou can use our console to input your metering without any engineer requirements to connect with cloud by yourself.\n::\n\n::suger-home-img\n---\nicon: 'https://uploads-ssl.webflow.com/6280284db2137d2c42b7c4b1/62803e6c5ce3f006689b6ced_Screen%20Shot%202022-05-14%20at%204.42.26%20PM.png'\ncategory: img\n---\n::\n::\n\n::suger-home-learn-guides\n\n#title\nAll features you will need\n\n::suger-home-community\n::\n\n::\n\n::suger-home-pricing\n#title\nOur pricing\n#pricing-card\n::suger-home-text-list\n---\ntextList: ['Features included','Multi Cloud marketplace integrations\n','Users - Unlimited','New Product listing - Unlimited','New private offer - Unlimited\n','Easy metering & billing - Unlimited','Contract upsell, renew & conversion - Unlimited','Access to Suger API s']\nbkColor: bg-white\ntextColor: '#2a1b49'\ntitleColor: '#000'\nsubtitleColor: '#000'\n---\n#title\nSmall & Medium Business\n#subtitle\nAlways Free\n::\n\n::suger-home-text-list\n---\ntextList: ['Features included','All features in SMB plan','Premium support and services / SLAs','Dedicated account manager','Dedicated onboarding','Sell with Resellers & Partners','Customize based your request']\nbkColor: bg-purple-900\ntextColor: '#ffffff'\ntitleColor: '#ffffff'\nsubtitleColor: '#ffffff'\n---\n#title\nEnterprise\n#subtitle\nContact Sales\n::\n\n::\n\n::suger-home-footer-cooperation\n---\nbackgroundColor: '#f5f5f5'\n---\n#title\nWe integrated with:\n\n#img-card\n::suger-home-footer-img\n---\nicon: 'https://uploads-ssl.webflow.com/6280284db2137d2c42b7c4b1/628e7ea6040ff079d8a33b50_aws-logo-square.png'\ncategory: img\n---\n::\n::suger-home-footer-img\n---\nicon: 'https://uploads-ssl.webflow.com/6280284db2137d2c42b7c4b1/628e7ecc354e97e31bab404a_azure%20logo%20square.png'\ncategory: img\n---\n::\n::suger-home-footer-img\n---\nicon: 'https://uploads-ssl.webflow.com/6280284db2137d2c42b7c4b1/62894ba1a00622d22974c73e_google%20cloud.png'\ncategory: img\n---\n::\n::suger-home-footer-img\n---\nicon: 'https://uploads-ssl.webflow.com/6280284db2137d2c42b7c4b1/62894b4709b48a68d8549122_slack.png'\ncategory: img\n---\n::\n\n::\n\n","ast":{"type":"root","children":[{"type":"text","value":"\n"},{"type":"element","tag":"home-hero","props":{},"children":[{"type":"element","tag":"template","props":{"v-slot:title":""},"children":[{"type":"element","tag":"prose-paragraph","props":{},"children":[{"type":"text","value":"Accelerate your SaaS Monetization"},{"type":"element","tag":"br","props":{},"children":[]},{"type":"text","value":"on Multi Cloud Marketplaces"}]}],"content":[{"type":"element","tag":"prose-paragraph","props":{},"children":[{"type":"text","value":"Accelerate your SaaS Monetization"},{"type":"element","tag":"br","props":{},"children":[]},{"type":"text","value":"on Multi Cloud Marketplaces"}]}]}]},{"type":"text","value":"\n"},{"type":"text","value":"\n"},{"type":"element","tag":"suger-main-img","props":{},"children":[]},{"type":"text","value":"\n"},{"type":"element","tag":"suger-home-features","props":{},"children":[{"type":"element","tag":"section-content-item","props":{"description":"You can use our console to report usage of your all your entitlements. We will make sure upload these reports for you to the cloud marketplace.","image":"https://uploads-ssl.webflow.com/6280284db2137d2c42b7c4b1/6280284db2137d52aab7c4ed_icons8-check-dollar-96%201.png","title":"Easy metering"},"children":[]},{"type":"element","tag":"section-content-item","props":{"description":"You don't need an engineer team to help you build payment to start  monetization. Just grant us access to your cloud and we will do all the onboarding for you.","image":"https://uploads-ssl.webflow.com/6280284db2137d2c42b7c4b1/6280284db2137db099b7c4f0_icons8-secure-96%201.png","title":"No Code onboarding"},"children":[]},{"type":"element","tag":"section-content-item","props":{"description":"Many business shift their SaaS purchase from local to cloud for easy management. By listing your product on cloud marketplace, you have access to a major audience.","image":"https://uploads-ssl.webflow.com/6280284db2137d2c42b7c4b1/6280284db2137d52aab7c4ed_icons8-check-dollar-96%201.png","title":"Increase your sales"},"children":[]},{"type":"element","tag":"section-content-item","props":{"description":"On our console, you can easily identify the potential audience for conversion, renewal and upsell opportunity.","image":"https://uploads-ssl.webflow.com/6280284db2137d2c42b7c4b1/6280284db2137d52aab7c4ed_icons8-check-dollar-96%201.png","title":"Manage your contracts"},"children":[]},{"type":"element","tag":"template","props":{"v-slot:title":""},"children":[{"type":"element","tag":"prose-paragraph","props":{},"children":[{"type":"text","value":"Check our main features"}]}],"content":[{"type":"element","tag":"prose-paragraph","props":{},"children":[{"type":"text","value":"Check our main features"}]}]},{"type":"element","tag":"template","props":{"v-slot:description":""},"children":[{"type":"element","tag":"prose-paragraph","props":{},"children":[{"type":"text","value":"Suger is the solution to help cloud marketplace SaaS seller integrate with cloud marketplace much faster & easier. We enable SaaS companies of all sizes to boost their SaaS monetization via the cloud marketplace."}]}],"content":[{"type":"element","tag":"prose-paragraph","props":{},"children":[{"type":"text","value":"Suger is the solution to help cloud marketplace SaaS seller integrate with cloud marketplace much faster & easier. We enable SaaS companies of all sizes to boost their SaaS monetization via the cloud marketplace."}]}]}]},{"type":"text","value":"\n"},{"type":"element","tag":"suger-home-product","props":{"category":"Partners"},"children":[{"type":"element","tag":"template","props":{"v-slot:partners-card":""},"children":[{"type":"element","tag":"suger-home-img","props":{"category":"img","icon":"https://uploads-ssl.webflow.com/6280284db2137d2c42b7c4b1/62803e0239e6f50160d2e67d_Screen%20Shot%202022-05-14%20at%204.40.38%20PM.png","srcSet":["https://uploads-ssl.webflow.com/6280284db2137d2c42b7c4b1/62803e0239e6f50160d2e67d_Screen%20Shot%202022-05-14%20at%204.40.38%20PM-p-500.png 500w","https://uploads-ssl.webflow.com/6280284db2137d2c42b7c4b1/62803e0239e6f50160d2e67d_Screen%20Shot%202022-05-14%20at%204.40.38%20PM-p-800.png 800w","https://uploads-ssl.webflow.com/6280284db2137d2c42b7c4b1/62803e0239e6f50160d2e67d_Screen%20Shot%202022-05-14%20at%204.40.38%20PM.png 998w"]},"children":[]},{"type":"element","tag":"suger-home-text","props":{},"children":[{"type":"element","tag":"template","props":{"v-slot:title":""},"children":[{"type":"element","tag":"prose-paragraph","props":{},"children":[{"type":"text","value":"Technology partners"}]}],"content":[{"type":"element","tag":"prose-paragraph","props":{},"children":[{"type":"text","value":"Technology partners"}]}]},{"type":"element","tag":"template","props":{"v-slot:description":""},"children":[{"type":"element","tag":"prose-paragraph","props":{},"children":[{"type":"text","value":"Technology partners offer services that empower Nuxt developers, such as CMS, Hosting, Database, and more."}]}],"content":[{"type":"element","tag":"prose-paragraph","props":{},"children":[{"type":"text","value":"Technology partners offer services that empower Nuxt developers, such as CMS, Hosting, Database, and more."}]}]}]},{"type":"element","tag":"suger-home-text","props":{},"children":[{"type":"element","tag":"template","props":{"v-slot:title":""},"children":[{"type":"element","tag":"prose-paragraph","props":{},"children":[{"type":"text","value":"Easy metering"}]}],"content":[{"type":"element","tag":"prose-paragraph","props":{},"children":[{"type":"text","value":"Easy metering"}]}]},{"type":"element","tag":"template","props":{"v-slot:description":""},"children":[{"type":"element","tag":"prose-paragraph","props":{},"children":[{"type":"text","value":"You can use our console to input your metering without any engineer requirements to connect with cloud by yourself."}]}],"content":[{"type":"element","tag":"prose-paragraph","props":{},"children":[{"type":"text","value":"You can use our console to input your metering without any engineer requirements to connect with cloud by yourself."}]}]}]},{"type":"element","tag":"suger-home-img","props":{"category":"img","icon":"https://uploads-ssl.webflow.com/6280284db2137d2c42b7c4b1/62803e6c5ce3f006689b6ced_Screen%20Shot%202022-05-14%20at%204.42.26%20PM.png"},"children":[]}],"content":[{"type":"element","tag":"suger-home-img","props":{"category":"img","icon":"https://uploads-ssl.webflow.com/6280284db2137d2c42b7c4b1/62803e0239e6f50160d2e67d_Screen%20Shot%202022-05-14%20at%204.40.38%20PM.png","srcSet":["https://uploads-ssl.webflow.com/6280284db2137d2c42b7c4b1/62803e0239e6f50160d2e67d_Screen%20Shot%202022-05-14%20at%204.40.38%20PM-p-500.png 500w","https://uploads-ssl.webflow.com/6280284db2137d2c42b7c4b1/62803e0239e6f50160d2e67d_Screen%20Shot%202022-05-14%20at%204.40.38%20PM-p-800.png 800w","https://uploads-ssl.webflow.com/6280284db2137d2c42b7c4b1/62803e0239e6f50160d2e67d_Screen%20Shot%202022-05-14%20at%204.40.38%20PM.png 998w"]},"children":[]},{"type":"element","tag":"suger-home-text","props":{},"children":[{"type":"element","tag":"template","props":{"v-slot:title":""},"children":[{"type":"element","tag":"prose-paragraph","props":{},"children":[{"type":"text","value":"Technology partners"}]}],"content":[{"type":"element","tag":"prose-paragraph","props":{},"children":[{"type":"text","value":"Technology partners"}]}]},{"type":"element","tag":"template","props":{"v-slot:description":""},"children":[{"type":"element","tag":"prose-paragraph","props":{},"children":[{"type":"text","value":"Technology partners offer services that empower Nuxt developers, such as CMS, Hosting, Database, and more."}]}],"content":[{"type":"element","tag":"prose-paragraph","props":{},"children":[{"type":"text","value":"Technology partners offer services that empower Nuxt developers, such as CMS, Hosting, Database, and more."}]}]}]},{"type":"element","tag":"suger-home-text","props":{},"children":[{"type":"element","tag":"template","props":{"v-slot:title":""},"children":[{"type":"element","tag":"prose-paragraph","props":{},"children":[{"type":"text","value":"Easy metering"}]}],"content":[{"type":"element","tag":"prose-paragraph","props":{},"children":[{"type":"text","value":"Easy metering"}]}]},{"type":"element","tag":"template","props":{"v-slot:description":""},"children":[{"type":"element","tag":"prose-paragraph","props":{},"children":[{"type":"text","value":"You can use our console to input your metering without any engineer requirements to connect with cloud by yourself."}]}],"content":[{"type":"element","tag":"prose-paragraph","props":{},"children":[{"type":"text","value":"You can use our console to input your metering without any engineer requirements to connect with cloud by yourself."}]}]}]},{"type":"element","tag":"suger-home-img","props":{"category":"img","icon":"https://uploads-ssl.webflow.com/6280284db2137d2c42b7c4b1/62803e6c5ce3f006689b6ced_Screen%20Shot%202022-05-14%20at%204.42.26%20PM.png"},"children":[]}]}]},{"type":"text","value":"\n"},{"type":"element","tag":"suger-home-learn-guides","props":{},"children":[{"type":"element","tag":"template","props":{"v-slot:title":""},"children":[{"type":"element","tag":"prose-paragraph","props":{},"children":[{"type":"text","value":"All features you will need"}]},{"type":"element","tag":"suger-home-community","props":{},"children":[]}],"content":[{"type":"element","tag":"prose-paragraph","props":{},"children":[{"type":"text","value":"All features you will need"}]},{"type":"element","tag":"suger-home-community","props":{},"children":[]}]}]},{"type":"text","value":"\n"},{"type":"element","tag":"suger-home-pricing","props":{},"children":[{"type":"element","tag":"template","props":{"v-slot:title":""},"children":[{"type":"element","tag":"prose-paragraph","props":{},"children":[{"type":"text","value":"Our pricing"}]}],"content":[{"type":"element","tag":"prose-paragraph","props":{},"children":[{"type":"text","value":"Our pricing"}]}]},{"type":"element","tag":"template","props":{"v-slot:pricing-card":""},"children":[{"type":"element","tag":"suger-home-text-list","props":{":textList":"[\"Features included\",\"Multi Cloud marketplace integrations \",\"Users - Unlimited\",\"New Product listing - Unlimited\",\"New private offer - Unlimited \",\"Easy metering & billing - Unlimited\",\"Contract upsell, renew & conversion - Unlimited\",\"Access to Suger API s\"]","bkColor":"bg-white","subtitleColor":"#000","textColor":"#2a1b49","titleColor":"#000"},"children":[{"type":"element","tag":"template","props":{"v-slot:title":""},"children":[{"type":"element","tag":"prose-paragraph","props":{},"children":[{"type":"text","value":"Small & Medium Business"}]}],"content":[{"type":"element","tag":"prose-paragraph","props":{},"children":[{"type":"text","value":"Small & Medium Business"}]}]},{"type":"element","tag":"template","props":{"v-slot:subtitle":""},"children":[{"type":"element","tag":"prose-paragraph","props":{},"children":[{"type":"text","value":"Always Free"}]}],"content":[{"type":"element","tag":"prose-paragraph","props":{},"children":[{"type":"text","value":"Always Free"}]}]}]},{"type":"element","tag":"suger-home-text-list","props":{":textList":"[\"Features included\",\"All features in SMB plan\",\"Premium support and services / SLAs\",\"Dedicated account manager\",\"Dedicated onboarding\",\"Sell with Resellers & Partners\",\"Customize based your request\"]","bkColor":"bg-purple-900","subtitleColor":"#ffffff","textColor":"#ffffff","titleColor":"#ffffff"},"children":[{"type":"element","tag":"template","props":{"v-slot:title":""},"children":[{"type":"element","tag":"prose-paragraph","props":{},"children":[{"type":"text","value":"Enterprise"}]}],"content":[{"type":"element","tag":"prose-paragraph","props":{},"children":[{"type":"text","value":"Enterprise"}]}]},{"type":"element","tag":"template","props":{"v-slot:subtitle":""},"children":[{"type":"element","tag":"prose-paragraph","props":{},"children":[{"type":"text","value":"Contact Sales"}]}],"content":[{"type":"element","tag":"prose-paragraph","props":{},"children":[{"type":"text","value":"Contact Sales"}]}]}]}],"content":[{"type":"element","tag":"suger-home-text-list","props":{":textList":"[\"Features included\",\"Multi Cloud marketplace integrations \",\"Users - Unlimited\",\"New Product listing - Unlimited\",\"New private offer - Unlimited \",\"Easy metering & billing - Unlimited\",\"Contract upsell, renew & conversion - Unlimited\",\"Access to Suger API s\"]","bkColor":"bg-white","subtitleColor":"#000","textColor":"#2a1b49","titleColor":"#000"},"children":[{"type":"element","tag":"template","props":{"v-slot:title":""},"children":[{"type":"element","tag":"prose-paragraph","props":{},"children":[{"type":"text","value":"Small & Medium Business"}]}],"content":[{"type":"element","tag":"prose-paragraph","props":{},"children":[{"type":"text","value":"Small & Medium Business"}]}]},{"type":"element","tag":"template","props":{"v-slot:subtitle":""},"children":[{"type":"element","tag":"prose-paragraph","props":{},"children":[{"type":"text","value":"Always Free"}]}],"content":[{"type":"element","tag":"prose-paragraph","props":{},"children":[{"type":"text","value":"Always Free"}]}]}]},{"type":"element","tag":"suger-home-text-list","props":{":textList":"[\"Features included\",\"All features in SMB plan\",\"Premium support and services / SLAs\",\"Dedicated account manager\",\"Dedicated onboarding\",\"Sell with Resellers & Partners\",\"Customize based your request\"]","bkColor":"bg-purple-900","subtitleColor":"#ffffff","textColor":"#ffffff","titleColor":"#ffffff"},"children":[{"type":"element","tag":"template","props":{"v-slot:title":""},"children":[{"type":"element","tag":"prose-paragraph","props":{},"children":[{"type":"text","value":"Enterprise"}]}],"content":[{"type":"element","tag":"prose-paragraph","props":{},"children":[{"type":"text","value":"Enterprise"}]}]},{"type":"element","tag":"template","props":{"v-slot:subtitle":""},"children":[{"type":"element","tag":"prose-paragraph","props":{},"children":[{"type":"text","value":"Contact Sales"}]}],"content":[{"type":"element","tag":"prose-paragraph","props":{},"children":[{"type":"text","value":"Contact Sales"}]}]}]}]}]},{"type":"text","value":"\n"},{"type":"element","tag":"suger-home-footer-cooperation","props":{"backgroundColor":"#f5f5f5"},"children":[{"type":"element","tag":"template","props":{"v-slot:title":""},"children":[{"type":"element","tag":"prose-paragraph","props":{},"children":[{"type":"text","value":"We integrated with:"}]}],"content":[{"type":"element","tag":"prose-paragraph","props":{},"children":[{"type":"text","value":"We integrated with:"}]}]},{"type":"element","tag":"template","props":{"v-slot:img-card":""},"children":[{"type":"element","tag":"suger-home-footer-img","props":{"category":"img","icon":"https://uploads-ssl.webflow.com/6280284db2137d2c42b7c4b1/628e7ea6040ff079d8a33b50_aws-logo-square.png"},"children":[]},{"type":"element","tag":"suger-home-footer-img","props":{"category":"img","icon":"https://uploads-ssl.webflow.com/6280284db2137d2c42b7c4b1/628e7ecc354e97e31bab404a_azure%20logo%20square.png"},"children":[]},{"type":"element","tag":"suger-home-footer-img","props":{"category":"img","icon":"https://uploads-ssl.webflow.com/6280284db2137d2c42b7c4b1/62894ba1a00622d22974c73e_google%20cloud.png"},"children":[]},{"type":"element","tag":"suger-home-footer-img","props":{"category":"img","icon":"https://uploads-ssl.webflow.com/6280284db2137d2c42b7c4b1/62894b4709b48a68d8549122_slack.png"},"children":[]}],"content":[{"type":"element","tag":"suger-home-footer-img","props":{"category":"img","icon":"https://uploads-ssl.webflow.com/6280284db2137d2c42b7c4b1/628e7ea6040ff079d8a33b50_aws-logo-square.png"},"children":[]},{"type":"element","tag":"suger-home-footer-img","props":{"category":"img","icon":"https://uploads-ssl.webflow.com/6280284db2137d2c42b7c4b1/628e7ecc354e97e31bab404a_azure%20logo%20square.png"},"children":[]},{"type":"element","tag":"suger-home-footer-img","props":{"category":"img","icon":"https://uploads-ssl.webflow.com/6280284db2137d2c42b7c4b1/62894ba1a00622d22974c73e_google%20cloud.png"},"children":[]},{"type":"element","tag":"suger-home-footer-img","props":{"category":"img","icon":"https://uploads-ssl.webflow.com/6280284db2137d2c42b7c4b1/62894b4709b48a68d8549122_slack.png"},"children":[]}]}]}]},"toc":{"title":"","searchDepth":2,"depth":2,"links":[]}}}